MANIFEST.in
README.rst
requirements.txt
setup.py
sqlformatter.py
sqlformatter.egg-info/PKG-INFO
sqlformatter.egg-info/SOURCES.txt
sqlformatter.egg-info/dependency_links.txt
sqlformatter.egg-info/not-zip-safe
sqlformatter.egg-info/requires.txt
sqlformatter.egg-info/top_level.txt