Metadata-Version: 1.1
Name: sqlformatter
Version: 1.1
Summary: SQLFormatter: Beautiful colored SQL staments for logging
Home-page: http://github.com/henriquebastos/sqlformatter/
Author: Henrique Bastos
Author-email: henrique@bastos.net
License: MIT
Platform: any
Classifier: Development Status :: 5 - Production/Stable
Classifier: Intended Audience :: Developers
Classifier: License :: OSI Approved :: MIT License
Classifier: Natural Language :: English
Classifier: Operating System :: OS Independent
Classifier: Programming Language :: Python
Classifier: Topic :: Software Development :: Libraries
